aisdb-1.7.2.dist-info/METADATA
aisdb-1.7.2.dist-info/WHEEL
aisdb-1.7.2.dist-info/license_files/LICENSE
aisdb/database/decoder.py
aisdb/database/sqlfcn_callbacks.py
aisdb/database/__init__.py
aisdb/database/dbqry.py
aisdb/database/create_tables.py
aisdb/database/dbconn.py
aisdb/database/sqlfcn.py
aisdb/database/sql_query_strings.py
aisdb/track_gen.py
aisdb/webdata/_scraper.py
aisdb/webdata/__init__.py
aisdb/webdata/load_raster.py
aisdb/webdata/marinetraffic.py
aisdb/webdata/bathymetry.py
aisdb/webdata/shore_dist.py
aisdb/network_graph.py
aisdb/tests/testdata/test_data_20211101.nm4.gz
aisdb/tests/testdata/test_data_20211101.nm4
aisdb/tests/test_009_wsa.py
aisdb/tests/test_010_network_graph.py
aisdb/tests/test_001_postgres.py
aisdb/tests/test_012_interp.py
aisdb/tests/__init__.py
aisdb/tests/test_015_raster_dist.py
aisdb/tests/test_011_ui.py
aisdb/tests/test_008_interp.py
aisdb/tests/test_003_createtables.py
aisdb/tests/test_006_gis.py
aisdb/tests/test_013_proc_util.py
aisdb/tests/test_007_trackgen.py
aisdb/tests/create_testing_data.py
aisdb/tests/test_016_bathymetry.py
aisdb/tests/test_014_marinetraffic.py
aisdb/tests/test_005_dbqry.py
aisdb/tests/test_004_sqlfcn.py
aisdb/tests/test_002_decode.py
aisdb/receiver.py
aisdb/__init__.py
aisdb/denoising_encoder.py
aisdb/aisdb_sql/createtable_webdata_marinetraffic.sql
aisdb/aisdb_sql/createtable_static_aggregate.sql
aisdb/aisdb_sql/insert_webdata_marinetraffic.sql
aisdb/aisdb_sql/cte_dynamic_clusteredidx.sql
aisdb/aisdb_sql/createtable_griddata.sql
aisdb/aisdb_sql/coarsetype.sql
aisdb/aisdb_sql/select_merged_all.sql
aisdb/aisdb_sql/cte_coarsetype.sql
aisdb/aisdb_sql/cte_static.sql
aisdb/aisdb_sql/psql_createtable_static.sql
aisdb/aisdb_sql/createtable_static.sql
aisdb/aisdb_sql/cte_static_aggregate.sql
aisdb/aisdb_sql/select_join_dynamic_static_clusteredidx.sql
aisdb/aisdb_sql/insert_static.sql
aisdb/aisdb_sql/psql_static_trigger.sql
aisdb/aisdb_sql/select_static_join_webdata.sql
aisdb/aisdb_sql/psql_createtable_dynamic_noindex.sql
aisdb/aisdb_sql/select_columns_static.sql
aisdb/aisdb_sql/psql_dynamic_trigger.sql
aisdb-1.7.2.dist-info/RECORD
