Metadata-Version: 2.3
Name: aisdb
Version: 1.7.2
Classifier: Operating System :: POSIX :: Linux
Classifier: Programming Language :: Python :: 3.8
Classifier: Programming Language :: Python :: 3.9
Classifier: Topic :: Scientific/Engineering :: Information Analysis
Classifier: Topic :: Utilities
Classifier: Programming Language :: JavaScript
Classifier: Topic :: Scientific/Engineering :: GIS
Classifier: Intended Audience :: Developers
Classifier: Intended Audience :: Science/Research
Classifier: Programming Language :: SQL
Classifier: License :: OSI Approved :: GNU Affero General Public License v3 or later (AGPLv3+)
Classifier: Topic :: Database :: Database Engines/Servers
Classifier: Topic :: Database :: Front-Ends
Classifier: Programming Language :: Python :: 3.10
Classifier: Programming Language :: Rust
Requires-Dist: markupsafe
Requires-Dist: flask
Requires-Dist: packaging
Requires-Dist: pillow
Requires-Dist: requests
Requires-Dist: selenium
Requires-Dist: shapely
Requires-Dist: toml
Requires-Dist: tqdm
Requires-Dist: numpy
Requires-Dist: webdriver-manager
Requires-Dist: psycopg
Requires-Dist: psycopg[binary]
Requires-Dist: python-dateutil
Requires-Dist: orjson
Requires-Dist: websockets
Requires-Dist: beautifulsoup4
Requires-Dist: pyproj
Requires-Dist: py7zr
Requires-Dist: coverage ; extra == 'test'
Requires-Dist: pytest ; extra == 'test'
Requires-Dist: pytest-cov ; extra == 'test'
Requires-Dist: pytest-dotenv ; extra == 'test'
Requires-Dist: sphinx ; extra == 'docs'
Requires-Dist: sphinx-rtd-theme ; extra == 'docs'
Provides-Extra: test
Provides-Extra: docs
Provides-Extra: devel
License-File: LICENSE
Summary: Smart AIS data storage and integration
Author-email: "[AISViz] Making vessels tracking data available to everyone" <aisviz@dal.ca>
Requires-Python: >=3.8
Project-URL: homepage, https://aisviz.cs.dal.ca/
Project-URL: repository, https://github.com/AISViz/AISdb
Project-URL: tutorials, https://aisviz.gitbook.io/tutorials/
Project-URL: documentation, https://aisviz.gitbook.io/documentation/
